[
  {
    "node_id": 51,
    "task_id": 1,
    "start_time": 0.0,
    "end_time": 3.2066666666666665e-07,
    "dependencies": []
  },
  {
    "node_id": 51,
    "task_id": 3,
    "start_time": 0.0,
    "end_time": 3.32e-07,
    "dependencies": []
  },
  {
    "node_id": 51,
    "task_id": 9,
    "start_time": 0.0,
    "end_time": 4.24e-07,
    "dependencies": []
  },
  {
    "node_id": 51,
    "task_id": 15,
    "start_time": 107.00001775,
    "end_time": 107.00001812066667,
    "dependencies": [
      {
        "task_id": 2,
        "path_id": "49721",
        "message_size": 57.0
      }
    ]
  },
  {
    "node_id": 51,
    "task_id": 7,
    "start_time": 115.000000332,
    "end_time": 115.00000079333333,
    "dependencies": [
      {
        "task_id": 3,
        "path_id": "183650",
        "message_size": 65.0
      }
    ]
  },
  {
    "node_id": 51,
    "task_id": 5,
    "start_time": 115.000000596,
    "end_time": 115.00000108266667,
    "dependencies": [
      {
        "task_id": 1,
        "path_id": "183650",
        "message_size": 65.0
      }
    ]
  },
  {
    "node_id": 51,
    "task_id": 17,
    "start_time": 222.00001812066665,
    "end_time": 222.00001821866664,
    "dependencies": [
      {
        "task_id": 2,
        "path_id": "49721",
        "message_size": 57.0
      },
      {
        "task_id": 6,
        "path_id": "49721",
        "message_size": 57.0
      },
      {
        "task_id": 15,
        "path_id": "183650",
        "message_size": 65.0
      }
    ]
  },
  {
    "node_id": 51,
    "task_id": 19,
    "start_time": 334.0000015651667,
    "end_time": 334.0000017431667,
    "dependencies": [
      {
        "task_id": 10,
        "path_id": "49721",
        "message_size": 57.0
      },
      {
        "task_id": 3,
        "path_id": "183650",
        "message_size": 65.0
      },
      {
        "task_id": 16,
        "path_id": "00",
        "message_size": 17.0
      },
      {
        "task_id": 17,
        "path_id": "183650",
        "message_size": 65.0
      },
      {
        "task_id": 14,
        "path_id": "00",
        "message_size": 17.0
      },
      {
        "task_id": 11,
        "path_id": "00",
        "message_size": 17.0
      },
      {
        "task_id": 6,
        "path_id": "49721",
        "message_size": 57.0
      }
    ]
  },
  {
    "node_id": 51,
    "task_id": 24,
    "start_time": 334.0000017431667,
    "end_time": 334.00000224850004,
    "dependencies": [
      {
        "task_id": 16,
        "path_id": "00",
        "message_size": 17.0
      },
      {
        "task_id": 5,
        "path_id": "183650",
        "message_size": 65.0
      },
      {
        "task_id": 11,
        "path_id": "00",
        "message_size": 17.0
      },
      {
        "task_id": 18,
        "path_id": "00",
        "message_size": 17.0
      },
      {
        "task_id": 15,
        "path_id": "183650",
        "message_size": 65.0
      },
      {
        "task_id": 19,
        "path_id": "183650",
        "message_size": 65.0
      },
      {
        "task_id": 2,
        "path_id": "49721",
        "message_size": 57.0
      }
    ]
  },
  {
    "node_id": 51,
    "task_id": 30,
    "start_time": 342.0000011458333,
    "end_time": 342.0000013498333,
    "dependencies": [
      {
        "task_id": 10,
        "path_id": "49721",
        "message_size": 57.0
      },
      {
        "task_id": 3,
        "path_id": "183650",
        "message_size": 65.0
      },
      {
        "task_id": 25,
        "path_id": "00",
        "message_size": 17.0
      },
      {
        "task_id": 23,
        "path_id": "183650",
        "message_size": 65.0
      },
      {
        "task_id": 27,
        "path_id": "49721",
        "message_size": 57.0
      },
      {
        "task_id": 1,
        "path_id": "183650",
        "message_size": 65.0
      },
      {
        "task_id": 5,
        "path_id": "183650",
        "message_size": 65.0
      },
      {
        "task_id": 21,
        "path_id": "183650",
        "message_size": 65.0
      },
      {
        "task_id": 12,
        "path_id": "00",
        "message_size": 17.0
      }
    ]
  },
  {
    "node_id": 51,
    "task_id": 36,
    "start_time": 342.0000011458333,
    "end_time": 342.0000012345,
    "dependencies": [
      {
        "task_id": 3,
        "path_id": "183650",
        "message_size": 65.0
      },
      {
        "task_id": 25,
        "path_id": "00",
        "message_size": 17.0
      },
      {
        "task_id": 27,
        "path_id": "49721",
        "message_size": 57.0
      },
      {
        "task_id": 14,
        "path_id": "00",
        "message_size": 17.0
      },
      {
        "task_id": 18,
        "path_id": "00",
        "message_size": 17.0
      },
      {
        "task_id": 4,
        "path_id": "00",
        "message_size": 17.0
      }
    ]
  },
  {
    "node_id": 51,
    "task_id": 23,
    "start_time": 399.0000124761667,
    "end_time": 399.0000128341667,
    "dependencies": [
      {
        "task_id": 10,
        "path_id": "49721",
        "message_size": 57.0
      },
      {
        "task_id": 15,
        "path_id": "183650",
        "message_size": 65.0
      },
      {
        "task_id": 22,
        "path_id": "00",
        "message_size": 17.0
      },
      {
        "task_id": 4,
        "path_id": "00",
        "message_size": 17.0
      }
    ]
  },
  {
    "node_id": 51,
    "task_id": 21,
    "start_time": 399.00001248283337,
    "end_time": 399.0000126221667,
    "dependencies": [
      {
        "task_id": 20,
        "path_id": "00",
        "message_size": 17.0
      },
      {
        "task_id": 3,
        "path_id": "183650",
        "message_size": 65.0
      },
      {
        "task_id": 13,
        "path_id": "00",
        "message_size": 17.0
      },
      {
        "task_id": 17,
        "path_id": "183650",
        "message_size": 65.0
      },
      {
        "task_id": 8,
        "path_id": "49721",
        "message_size": 57.0
      },
      {
        "task_id": 11,
        "path_id": "00",
        "message_size": 17.0
      },
      {
        "task_id": 15,
        "path_id": "183650",
        "message_size": 65.0
      }
    ]
  },
  {
    "node_id": 51,
    "task_id": 33,
    "start_time": 471.0000163333333,
    "end_time": 471.0000167113333,
    "dependencies": [
      {
        "task_id": 7,
        "path_id": "183650",
        "message_size": 65.0
      },
      {
        "task_id": 17,
        "path_id": "183650",
        "message_size": 65.0
      },
      {
        "task_id": 28,
        "path_id": "49721",
        "message_size": 57.0
      }
    ]
  },
  {
    "node_id": 51,
    "task_id": 44,
    "start_time": 472.00001268908335,
    "end_time": 472.00001307975003,
    "dependencies": [
      {
        "task_id": 26,
        "path_id": "00",
        "message_size": 17.0
      },
      {
        "task_id": 25,
        "path_id": "00",
        "message_size": 17.0
      },
      {
        "task_id": 43,
        "path_id": "00",
        "message_size": 17.0
      },
      {
        "task_id": 9,
        "path_id": "183650",
        "message_size": 65.0
      },
      {
        "task_id": 11,
        "path_id": "00",
        "message_size": 17.0
      },
      {
        "task_id": 19,
        "path_id": "183650",
        "message_size": 65.0
      }
    ]
  },
  {
    "node_id": 51,
    "task_id": 38,
    "start_time": 528.0000233578334,
    "end_time": 528.0000236331666,
    "dependencies": [
      {
        "task_id": 3,
        "path_id": "183650",
        "message_size": 65.0
      },
      {
        "task_id": 29,
        "path_id": "00",
        "message_size": 17.0
      },
      {
        "task_id": 37,
        "path_id": "00",
        "message_size": 17.0
      },
      {
        "task_id": 23,
        "path_id": "183650",
        "message_size": 65.0
      },
      {
        "task_id": 16,
        "path_id": "00",
        "message_size": 17.0
      },
      {
        "task_id": 17,
        "path_id": "183650",
        "message_size": 65.0
      },
      {
        "task_id": 5,
        "path_id": "183650",
        "message_size": 65.0
      },
      {
        "task_id": 11,
        "path_id": "00",
        "message_size": 17.0
      },
      {
        "task_id": 4,
        "path_id": "00",
        "message_size": 17.0
      },
      {
        "task_id": 34,
        "path_id": "49721",
        "message_size": 57.0
      },
      {
        "task_id": 12,
        "path_id": "00",
        "message_size": 17.0
      }
    ]
  },
  {
    "node_id": 51,
    "task_id": 40,
    "start_time": 586.0000167113333,
    "end_time": 586.0000171746666,
    "dependencies": [
      {
        "task_id": 26,
        "path_id": "00",
        "message_size": 17.0
      },
      {
        "task_id": 10,
        "path_id": "49721",
        "message_size": 57.0
      },
      {
        "task_id": 7,
        "path_id": "183650",
        "message_size": 65.0
      },
      {
        "task_id": 5,
        "path_id": "183650",
        "message_size": 65.0
      },
      {
        "task_id": 21,
        "path_id": "183650",
        "message_size": 65.0
      },
      {
        "task_id": 33,
        "path_id": "183650",
        "message_size": 65.0
      },
      {
        "task_id": 4,
        "path_id": "00",
        "message_size": 17.0
      },
      {
        "task_id": 31,
        "path_id": "00",
        "message_size": 17.0
      },
      {
        "task_id": 34,
        "path_id": "49721",
        "message_size": 57.0
      },
      {
        "task_id": 38,
        "path_id": "183650",
        "message_size": 65.0
      },
      {
        "task_id": 35,
        "path_id": "49721",
        "message_size": 57.0
      },
      {
        "task_id": 28,
        "path_id": "49721",
        "message_size": 57.0
      }
    ]
  },
  {
    "node_id": 52,
    "task_id": 0,
    "start_time": 0.0,
    "end_time": 1.170833333333333e-07,
    "dependencies": []
  },
  {
    "node_id": 52,
    "task_id": 11,
    "start_time": 104.000000424,
    "end_time": 104.00000070233334,
    "dependencies": [
      {
        "task_id": 2,
        "path_id": "51341",
        "message_size": 31.0
      },
      {
        "task_id": 9,
        "path_id": "49711",
        "message_size": 54.0
      },
      {
        "task_id": 3,
        "path_id": "49711",
        "message_size": 54.0
      }
    ]
  },
  {
    "node_id": 52,
    "task_id": 14,
    "start_time": 104.000000424,
    "end_time": 104.00000049858335,
    "dependencies": [
      {
        "task_id": 2,
        "path_id": "51341",
        "message_size": 31.0
      },
      {
        "task_id": 9,
        "path_id": "49711",
        "message_size": 54.0
      },
      {
        "task_id": 10,
        "path_id": "51341",
        "message_size": 31.0
      }
    ]
  },
  {
    "node_id": 52,
    "task_id": 4,
    "start_time": 104.000000596,
    "end_time": 104.00000083058335,
    "dependencies": [
      {
        "task_id": 1,
        "path_id": "49711",
        "message_size": 54.0
      },
      {
        "task_id": 3,
        "path_id": "49711",
        "message_size": 54.0
      }
    ]
  },
  {
    "node_id": 52,
    "task_id": 12,
    "start_time": 219.00000079333333,
    "end_time": 219.0000008833333,
    "dependencies": [
      {
        "task_id": 1,
        "path_id": "49711",
        "message_size": 54.0
      },
      {
        "task_id": 7,
        "path_id": "49711",
        "message_size": 54.0
      },
      {
        "task_id": 3,
        "path_id": "49711",
        "message_size": 54.0
      }
    ]
  },
  {
    "node_id": 52,
    "task_id": 13,
    "start_time": 219.00000108266667,
    "end_time": 219.00000132141668,
    "dependencies": [
      {
        "task_id": 2,
        "path_id": "51341",
        "message_size": 31.0
      },
      {
        "task_id": 6,
        "path_id": "51341",
        "message_size": 31.0
      },
      {
        "task_id": 7,
        "path_id": "49711",
        "message_size": 54.0
      },
      {
        "task_id": 5,
        "path_id": "49711",
        "message_size": 54.0
      }
    ]
  },
  {
    "node_id": 52,
    "task_id": 29,
    "start_time": 219.00000108266667,
    "end_time": 219.00000134433333,
    "dependencies": [
      {
        "task_id": 8,
        "path_id": "51341",
        "message_size": 31.0
      },
      {
        "task_id": 5,
        "path_id": "49711",
        "message_size": 54.0
      },
      {
        "task_id": 10,
        "path_id": "51341",
        "message_size": 31.0
      },
      {
        "task_id": 3,
        "path_id": "49711",
        "message_size": 54.0
      }
    ]
  },
  {
    "node_id": 52,
    "task_id": 41,
    "start_time": 219.00000108266667,
    "end_time": 219.00000135308335,
    "dependencies": [
      {
        "task_id": 5,
        "path_id": "49711",
        "message_size": 54.0
      },
      {
        "task_id": 0,
        "path_id": "183660",
        "message_size": 23.0
      }
    ]
  },
  {
    "node_id": 52,
    "task_id": 16,
    "start_time": 292.0000013214167,
    "end_time": 292.0000015651667,
    "dependencies": [
      {
        "task_id": 13,
        "path_id": "183660",
        "message_size": 23.0
      },
      {
        "task_id": 6,
        "path_id": "51341",
        "message_size": 31.0
      },
      {
        "task_id": 11,
        "path_id": "183660",
        "message_size": 23.0
      }
    ]
  },
  {
    "node_id": 52,
    "task_id": 25,
    "start_time": 292.0000013214167,
    "end_time": 292.00000154266667,
    "dependencies": [
      {
        "task_id": 12,
        "path_id": "183660",
        "message_size": 23.0
      },
      {
        "task_id": 23,
        "path_id": "49711",
        "message_size": 54.0
      },
      {
        "task_id": 15,
        "path_id": "49711",
        "message_size": 54.0
      },
      {
        "task_id": 13,
        "path_id": "183660",
        "message_size": 23.0
      },
      {
        "task_id": 9,
        "path_id": "49711",
        "message_size": 54.0
      }
    ]
  },
  {
    "node_id": 52,
    "task_id": 18,
    "start_time": 316.0000118675,
    "end_time": 316.00001209916667,
    "dependencies": [
      {
        "task_id": 14,
        "path_id": "183660",
        "message_size": 23.0
      },
      {
        "task_id": 17,
        "path_id": "49711",
        "message_size": 54.0
      },
      {
        "task_id": 7,
        "path_id": "49711",
        "message_size": 54.0
      },
      {
        "task_id": 16,
        "path_id": "183660",
        "message_size": 23.0
      },
      {
        "task_id": 11,
        "path_id": "183660",
        "message_size": 23.0
      }
    ]
  },
  {
    "node_id": 52,
    "task_id": 20,
    "start_time": 332.0000122449167,
    "end_time": 332.00001248283337,
    "dependencies": [
      {
        "task_id": 18,
        "path_id": "183660",
        "message_size": 23.0
      },
      {
        "task_id": 1,
        "path_id": "49711",
        "message_size": 54.0
      },
      {
        "task_id": 15,
        "path_id": "49711",
        "message_size": 54.0
      },
      {
        "task_id": 16,
        "path_id": "183660",
        "message_size": 23.0
      },
      {
        "task_id": 6,
        "path_id": "51341",
        "message_size": 31.0
      },
      {
        "task_id": 8,
        "path_id": "51341",
        "message_size": 31.0
      },
      {
        "task_id": 9,
        "path_id": "49711",
        "message_size": 54.0
      }
    ]
  },
  {
    "node_id": 52,
    "task_id": 22,
    "start_time": 332.0000122449167,
    "end_time": 332.0000124761667,
    "dependencies": [
      {
        "task_id": 18,
        "path_id": "183660",
        "message_size": 23.0
      },
      {
        "task_id": 12,
        "path_id": "183660",
        "message_size": 23.0
      },
      {
        "task_id": 15,
        "path_id": "49711",
        "message_size": 54.0
      },
      {
        "task_id": 4,
        "path_id": "183660",
        "message_size": 23.0
      },
      {
        "task_id": 8,
        "path_id": "51341",
        "message_size": 31.0
      },
      {
        "task_id": 19,
        "path_id": "49711",
        "message_size": 54.0
      }
    ]
  },
  {
    "node_id": 52,
    "task_id": 32,
    "start_time": 348.00000113458333,
    "end_time": 348.0000013025,
    "dependencies": [
      {
        "task_id": 4,
        "path_id": "183660",
        "message_size": 23.0
      },
      {
        "task_id": 19,
        "path_id": "49711",
        "message_size": 54.0
      },
      {
        "task_id": 18,
        "path_id": "183660",
        "message_size": 23.0
      },
      {
        "task_id": 31,
        "path_id": "183660",
        "message_size": 23.0
      }
    ]
  },
  {
    "node_id": 52,
    "task_id": 37,
    "start_time": 348.00000113458333,
    "end_time": 348.00000133541664,
    "dependencies": [
      {
        "task_id": 14,
        "path_id": "183660",
        "message_size": 23.0
      },
      {
        "task_id": 31,
        "path_id": "183660",
        "message_size": 23.0
      },
      {
        "task_id": 36,
        "path_id": "49711",
        "message_size": 54.0
      },
      {
        "task_id": 4,
        "path_id": "183660",
        "message_size": 23.0
      },
      {
        "task_id": 9,
        "path_id": "49711",
        "message_size": 54.0
      },
      {
        "task_id": 3,
        "path_id": "49711",
        "message_size": 54.0
      }
    ]
  },
  {
    "node_id": 52,
    "task_id": 26,
    "start_time": 405.0000124761667,
    "end_time": 405.0000126195,
    "dependencies": [
      {
        "task_id": 22,
        "path_id": "183660",
        "message_size": 23.0
      },
      {
        "task_id": 7,
        "path_id": "49711",
        "message_size": 54.0
      },
      {
        "task_id": 12,
        "path_id": "183660",
        "message_size": 23.0
      },
      {
        "task_id": 0,
        "path_id": "183660",
        "message_size": 23.0
      },
      {
        "task_id": 6,
        "path_id": "51341",
        "message_size": 31.0
      },
      {
        "task_id": 5,
        "path_id": "49711",
        "message_size": 54.0
      },
      {
        "task_id": 3,
        "path_id": "49711",
        "message_size": 54.0
      }
    ]
  },
  {
    "node_id": 52,
    "task_id": 45,
    "start_time": 445.00003377083334,
    "end_time": 445.00003382458334,
    "dependencies": [
      {
        "task_id": 22,
        "path_id": "183660",
        "message_size": 23.0
      },
      {
        "task_id": 17,
        "path_id": "49711",
        "message_size": 54.0
      },
      {
        "task_id": 32,
        "path_id": "183660",
        "message_size": 23.0
      },
      {
        "task_id": 42,
        "path_id": "51341",
        "message_size": 31.0
      },
      {
        "task_id": 2,
        "path_id": "51341",
        "message_size": 31.0
      },
      {
        "task_id": 8,
        "path_id": "51341",
        "message_size": 31.0
      },
      {
        "task_id": 28,
        "path_id": "51341",
        "message_size": 31.0
      },
      {
        "task_id": 39,
        "path_id": "183660",
        "message_size": 23.0
      }
    ]
  },
  {
    "node_id": 52,
    "task_id": 31,
    "start_time": 450.0000128341667,
    "end_time": 450.0000130441667,
    "dependencies": [
      {
        "task_id": 7,
        "path_id": "49711",
        "message_size": 54.0
      },
      {
        "task_id": 12,
        "path_id": "183660",
        "message_size": 23.0
      },
      {
        "task_id": 23,
        "path_id": "49711",
        "message_size": 54.0
      },
      {
        "task_id": 6,
        "path_id": "51341",
        "message_size": 31.0
      },
      {
        "task_id": 8,
        "path_id": "51341",
        "message_size": 31.0
      }
    ]
  },
  {
    "node_id": 52,
    "task_id": 47,
    "start_time": 518.0000338245834,
    "end_time": 518.000034075,
    "dependencies": [
      {
        "task_id": 37,
        "path_id": "183660",
        "message_size": 23.0
      },
      {
        "task_id": 7,
        "path_id": "49711",
        "message_size": 54.0
      },
      {
        "task_id": 13,
        "path_id": "183660",
        "message_size": 23.0
      },
      {
        "task_id": 24,
        "path_id": "49711",
        "message_size": 54.0
      },
      {
        "task_id": 29,
        "path_id": "183660",
        "message_size": 23.0
      },
      {
        "task_id": 2,
        "path_id": "51341",
        "message_size": 31.0
      },
      {
        "task_id": 45,
        "path_id": "183660",
        "message_size": 23.0
      },
      {
        "task_id": 19,
        "path_id": "49711",
        "message_size": 54.0
      },
      {
        "task_id": 10,
        "path_id": "51341",
        "message_size": 31.0
      }
    ]
  },
  {
    "node_id": 52,
    "task_id": 39,
    "start_time": 538.0000236331666,
    "end_time": 538.0000239660833,
    "dependencies": [
      {
        "task_id": 14,
        "path_id": "183660",
        "message_size": 23.0
      },
      {
        "task_id": 34,
        "path_id": "51341",
        "message_size": 31.0
      },
      {
        "task_id": 38,
        "path_id": "49711",
        "message_size": 54.0
      },
      {
        "task_id": 37,
        "path_id": "183660",
        "message_size": 23.0
      },
      {
        "task_id": 31,
        "path_id": "183660",
        "message_size": 23.0
      },
      {
        "task_id": 17,
        "path_id": "49711",
        "message_size": 54.0
      },
      {
        "task_id": 7,
        "path_id": "49711",
        "message_size": 54.0
      },
      {
        "task_id": 36,
        "path_id": "49711",
        "message_size": 54.0
      },
      {
        "task_id": 12,
        "path_id": "183660",
        "message_size": 23.0
      },
      {
        "task_id": 16,
        "path_id": "183660",
        "message_size": 23.0
      },
      {
        "task_id": 8,
        "path_id": "51341",
        "message_size": 31.0
      }
    ]
  },
  {
    "node_id": 52,
    "task_id": 43,
    "start_time": 575.0000167113333,
    "end_time": 575.0000169175833,
    "dependencies": [
      {
        "task_id": 34,
        "path_id": "51341",
        "message_size": 31.0
      },
      {
        "task_id": 9,
        "path_id": "49711",
        "message_size": 54.0
      },
      {
        "task_id": 25,
        "path_id": "183660",
        "message_size": 23.0
      },
      {
        "task_id": 1,
        "path_id": "49711",
        "message_size": 54.0
      },
      {
        "task_id": 41,
        "path_id": "183660",
        "message_size": 23.0
      },
      {
        "task_id": 31,
        "path_id": "183660",
        "message_size": 23.0
      },
      {
        "task_id": 17,
        "path_id": "49711",
        "message_size": 54.0
      },
      {
        "task_id": 36,
        "path_id": "49711",
        "message_size": 54.0
      },
      {
        "task_id": 12,
        "path_id": "183660",
        "message_size": 23.0
      },
      {
        "task_id": 21,
        "path_id": "49711",
        "message_size": 54.0
      },
      {
        "task_id": 33,
        "path_id": "49711",
        "message_size": 54.0
      },
      {
        "task_id": 23,
        "path_id": "49711",
        "message_size": 54.0
      },
      {
        "task_id": 20,
        "path_id": "183660",
        "message_size": 23.0
      },
      {
        "task_id": 11,
        "path_id": "183660",
        "message_size": 23.0
      }
    ]
  },
  {
    "node_id": 53,
    "task_id": 2,
    "start_time": 0.0,
    "end_time": 1.775e-05,
    "dependencies": []
  },
  {
    "node_id": 53,
    "task_id": 10,
    "start_time": 89.0000006175,
    "end_time": 89.0000088675,
    "dependencies": [
      {
        "task_id": 0,
        "path_id": "51343",
        "message_size": 39.0
      }
    ]
  },
  {
    "node_id": 53,
    "task_id": 6,
    "start_time": 105.000000332,
    "end_time": 105.0000117695,
    "dependencies": [
      {
        "task_id": 3,
        "path_id": "49723",
        "message_size": 55.0
      },
      {
        "task_id": 0,
        "path_id": "51343",
        "message_size": 39.0
      }
    ]
  },
  {
    "node_id": 53,
    "task_id": 8,
    "start_time": 109.00001775,
    "end_time": 109.00002825,
    "dependencies": [
      {
        "task_id": 1,
        "path_id": "49723",
        "message_size": 55.0
      },
      {
        "task_id": 2,
        "path_id": "183670",
        "message_size": 59.0
      }
    ]
  },
  {
    "node_id": 53,
    "task_id": 35,
    "start_time": 193.00000056658334,
    "end_time": 193.00001419158335,
    "dependencies": [
      {
        "task_id": 14,
        "path_id": "51343",
        "message_size": 39.0
      },
      {
        "task_id": 10,
        "path_id": "183670",
        "message_size": 59.0
      },
      {
        "task_id": 4,
        "path_id": "51343",
        "message_size": 39.0
      },
      {
        "task_id": 0,
        "path_id": "51343",
        "message_size": 39.0
      }
    ]
  },
  {
    "node_id": 53,
    "task_id": 27,
    "start_time": 212.00001812066665,
    "end_time": 212.00003049566664,
    "dependencies": [
      {
        "task_id": 1,
        "path_id": "49723",
        "message_size": 55.0
      },
      {
        "task_id": 15,
        "path_id": "49723",
        "message_size": 55.0
      }
    ]
  },
  {
    "node_id": 53,
    "task_id": 28,
    "start_time": 364.0000011458333,
    "end_time": 364.0000163333333,
    "dependencies": [
      {
        "task_id": 19,
        "path_id": "49723",
        "message_size": 55.0
      },
      {
        "task_id": 11,
        "path_id": "51343",
        "message_size": 39.0
      },
      {
        "task_id": 7,
        "path_id": "49723",
        "message_size": 55.0
      },
      {
        "task_id": 25,
        "path_id": "51343",
        "message_size": 39.0
      },
      {
        "task_id": 5,
        "path_id": "49723",
        "message_size": 55.0
      }
    ]
  },
  {
    "node_id": 53,
    "task_id": 42,
    "start_time": 364.0000011458333,
    "end_time": 364.00003377083334,
    "dependencies": [
      {
        "task_id": 9,
        "path_id": "49723",
        "message_size": 55.0
      },
      {
        "task_id": 14,
        "path_id": "51343",
        "message_size": 39.0
      },
      {
        "task_id": 23,
        "path_id": "49723",
        "message_size": 55.0
      },
      {
        "task_id": 25,
        "path_id": "51343",
        "message_size": 39.0
      }
    ]
  },
  {
    "node_id": 53,
    "task_id": 34,
    "start_time": 421.00001248283337,
    "end_time": 421.00002335783336,
    "dependencies": [
      {
        "task_id": 27,
        "path_id": "183670",
        "message_size": 59.0
      },
      {
        "task_id": 20,
        "path_id": "51343",
        "message_size": 39.0
      },
      {
        "task_id": 8,
        "path_id": "183670",
        "message_size": 59.0
      },
      {
        "task_id": 7,
        "path_id": "49723",
        "message_size": 55.0
      },
      {
        "task_id": 10,
        "path_id": "183670",
        "message_size": 59.0
      }
    ]
  },
  {
    "node_id": 53,
    "task_id": 46,
    "start_time": 577.00001307975,
    "end_time": 577.0000360172501,
    "dependencies": [
      {
        "task_id": 39,
        "path_id": "51343",
        "message_size": 39.0
      },
      {
        "task_id": 29,
        "path_id": "51343",
        "message_size": 39.0
      },
      {
        "task_id": 16,
        "path_id": "51343",
        "message_size": 39.0
      },
      {
        "task_id": 3,
        "path_id": "49723",
        "message_size": 55.0
      },
      {
        "task_id": 19,
        "path_id": "49723",
        "message_size": 55.0
      },
      {
        "task_id": 42,
        "path_id": "183670",
        "message_size": 59.0
      },
      {
        "task_id": 44,
        "path_id": "49723",
        "message_size": 55.0
      },
      {
        "task_id": 31,
        "path_id": "51343",
        "message_size": 39.0
      },
      {
        "task_id": 24,
        "path_id": "49723",
        "message_size": 55.0
      }
    ]
  },
  {
    "node_id": 53,
    "task_id": 48,
    "start_time": 577.00001307975,
    "end_time": 577.00004932975,
    "dependencies": [
      {
        "task_id": 35,
        "path_id": "183670",
        "message_size": 59.0
      },
      {
        "task_id": 27,
        "path_id": "183670",
        "message_size": 59.0
      },
      {
        "task_id": 13,
        "path_id": "51343",
        "message_size": 39.0
      },
      {
        "task_id": 19,
        "path_id": "49723",
        "message_size": 55.0
      },
      {
        "task_id": 38,
        "path_id": "49723",
        "message_size": 55.0
      },
      {
        "task_id": 44,
        "path_id": "49723",
        "message_size": 55.0
      },
      {
        "task_id": 1,
        "path_id": "49723",
        "message_size": 55.0
      },
      {
        "task_id": 17,
        "path_id": "49723",
        "message_size": 55.0
      },
      {
        "task_id": 7,
        "path_id": "49723",
        "message_size": 55.0
      },
      {
        "task_id": 21,
        "path_id": "49723",
        "message_size": 55.0
      },
      {
        "task_id": 15,
        "path_id": "49723",
        "message_size": 55.0
      },
      {
        "task_id": 0,
        "path_id": "51343",
        "message_size": 39.0
      }
    ]
  }
]