[
  {
    "node_id": 51,
    "task_id": 3,
    "start_time": 0.0,
    "end_time": 3.813333333333333e-07,
    "dependencies": []
  },
  {
    "node_id": 51,
    "task_id": 4,
    "start_time": 0.0,
    "end_time": 2.366666666666667e-07,
    "dependencies": []
  },
  {
    "node_id": 51,
    "task_id": 16,
    "start_time": 101.00000056333333,
    "end_time": 101.00000067399999,
    "dependencies": [
      {
        "task_id": 8,
        "path_id": "183650",
        "message_size": 51.0
      },
      {
        "task_id": 4,
        "path_id": "183650",
        "message_size": 51.0
      }
    ]
  },
  {
    "node_id": 51,
    "task_id": 9,
    "start_time": 103.000039875,
    "end_time": 103.000040059,
    "dependencies": [
      {
        "task_id": 2,
        "path_id": "49723",
        "message_size": 53.0
      }
    ]
  },
  {
    "node_id": 51,
    "task_id": 17,
    "start_time": 184.00000079325,
    "end_time": 184.00000106191666,
    "dependencies": [
      {
        "task_id": 10,
        "path_id": "49712",
        "message_size": 41.0
      },
      {
        "task_id": 5,
        "path_id": "49712",
        "message_size": 41.0
      }
    ]
  },
  {
    "node_id": 51,
    "task_id": 8,
    "start_time": 193.00004014541668,
    "end_time": 193.00004033208333,
    "dependencies": [
      {
        "task_id": 2,
        "path_id": "49723",
        "message_size": 53.0
      },
      {
        "task_id": 7,
        "path_id": "49712",
        "message_size": 41.0
      },
      {
        "task_id": 4,
        "path_id": "183650",
        "message_size": 51.0
      },
      {
        "task_id": 6,
        "path_id": "49712",
        "message_size": 41.0
      }
    ]
  },
  {
    "node_id": 51,
    "task_id": 23,
    "start_time": 288.00002067625,
    "end_time": 288.0000210529167,
    "dependencies": [
      {
        "task_id": 16,
        "path_id": "183650",
        "message_size": 51.0
      },
      {
        "task_id": 11,
        "path_id": "49712",
        "message_size": 41.0
      },
      {
        "task_id": 15,
        "path_id": "49712",
        "message_size": 41.0
      }
    ]
  },
  {
    "node_id": 51,
    "task_id": 25,
    "start_time": 288.00002067625,
    "end_time": 288.00002114358335,
    "dependencies": [
      {
        "task_id": 14,
        "path_id": "49723",
        "message_size": 53.0
      },
      {
        "task_id": 12,
        "path_id": "49712",
        "message_size": 41.0
      },
      {
        "task_id": 8,
        "path_id": "183650",
        "message_size": 51.0
      },
      {
        "task_id": 6,
        "path_id": "49712",
        "message_size": 41.0
      },
      {
        "task_id": 11,
        "path_id": "49712",
        "message_size": 41.0
      },
      {
        "task_id": 15,
        "path_id": "49712",
        "message_size": 41.0
      }
    ]
  },
  {
    "node_id": 51,
    "task_id": 48,
    "start_time": 288.00002067625,
    "end_time": 288.00002089558336,
    "dependencies": [
      {
        "task_id": 35,
        "path_id": "183650",
        "message_size": 51.0
      },
      {
        "task_id": 1,
        "path_id": "49723",
        "message_size": 53.0
      },
      {
        "task_id": 25,
        "path_id": "183650",
        "message_size": 51.0
      },
      {
        "task_id": 4,
        "path_id": "183650",
        "message_size": 51.0
      },
      {
        "task_id": 34,
        "path_id": "49712",
        "message_size": 41.0
      },
      {
        "task_id": 43,
        "path_id": "49723",
        "message_size": 53.0
      },
      {
        "task_id": 6,
        "path_id": "49712",
        "message_size": 41.0
      },
      {
        "task_id": 11,
        "path_id": "49712",
        "message_size": 41.0
      },
      {
        "task_id": 15,
        "path_id": "49712",
        "message_size": 41.0
      },
      {
        "task_id": 21,
        "path_id": "183650",
        "message_size": 51.0
      },
      {
        "task_id": 38,
        "path_id": "49712",
        "message_size": 41.0
      }
    ]
  },
  {
    "node_id": 51,
    "task_id": 31,
    "start_time": 299.00003338983333,
    "end_time": 299.0000339031667,
    "dependencies": [
      {
        "task_id": 4,
        "path_id": "183650",
        "message_size": 51.0
      },
      {
        "task_id": 2,
        "path_id": "49723",
        "message_size": 53.0
      },
      {
        "task_id": 24,
        "path_id": "49712",
        "message_size": 41.0
      },
      {
        "task_id": 11,
        "path_id": "49712",
        "message_size": 41.0
      },
      {
        "task_id": 22,
        "path_id": "49723",
        "message_size": 53.0
      },
      {
        "task_id": 18,
        "path_id": "49712",
        "message_size": 41.0
      },
      {
        "task_id": 21,
        "path_id": "183650",
        "message_size": 51.0
      },
      {
        "task_id": 3,
        "path_id": "183650",
        "message_size": 51.0
      }
    ]
  },
  {
    "node_id": 51,
    "task_id": 29,
    "start_time": 303.00000105066664,
    "end_time": 303.00000151266664,
    "dependencies": [
      {
        "task_id": 1,
        "path_id": "49723",
        "message_size": 53.0
      },
      {
        "task_id": 28,
        "path_id": "183650",
        "message_size": 51.0
      },
      {
        "task_id": 14,
        "path_id": "49723",
        "message_size": 53.0
      },
      {
        "task_id": 23,
        "path_id": "183650",
        "message_size": 51.0
      },
      {
        "task_id": 12,
        "path_id": "49712",
        "message_size": 41.0
      },
      {
        "task_id": 11,
        "path_id": "49712",
        "message_size": 41.0
      },
      {
        "task_id": 21,
        "path_id": "183650",
        "message_size": 51.0
      }
    ]
  },
  {
    "node_id": 51,
    "task_id": 30,
    "start_time": 303.00000105066664,
    "end_time": 303.0000013746667,
    "dependencies": [
      {
        "task_id": 5,
        "path_id": "49712",
        "message_size": 41.0
      },
      {
        "task_id": 24,
        "path_id": "49712",
        "message_size": 41.0
      },
      {
        "task_id": 16,
        "path_id": "183650",
        "message_size": 51.0
      },
      {
        "task_id": 23,
        "path_id": "183650",
        "message_size": 51.0
      }
    ]
  },
  {
    "node_id": 51,
    "task_id": 21,
    "start_time": 381.0000208954167,
    "end_time": 381.0000211594167,
    "dependencies": [
      {
        "task_id": 5,
        "path_id": "49712",
        "message_size": 41.0
      },
      {
        "task_id": 1,
        "path_id": "49723",
        "message_size": 53.0
      },
      {
        "task_id": 8,
        "path_id": "183650",
        "message_size": 51.0
      },
      {
        "task_id": 20,
        "path_id": "49712",
        "message_size": 41.0
      }
    ]
  },
  {
    "node_id": 51,
    "task_id": 28,
    "start_time": 381.0000208954167,
    "end_time": 381.00002130475,
    "dependencies": [
      {
        "task_id": 10,
        "path_id": "49712",
        "message_size": 41.0
      },
      {
        "task_id": 9,
        "path_id": "183650",
        "message_size": 51.0
      },
      {
        "task_id": 4,
        "path_id": "183650",
        "message_size": 51.0
      },
      {
        "task_id": 20,
        "path_id": "49712",
        "message_size": 41.0
      },
      {
        "task_id": 6,
        "path_id": "49712",
        "message_size": 41.0
      },
      {
        "task_id": 13,
        "path_id": "49723",
        "message_size": 53.0
      }
    ]
  },
  {
    "node_id": 51,
    "task_id": 33,
    "start_time": 381.0000208954167,
    "end_time": 381.0000214154167,
    "dependencies": [
      {
        "task_id": 19,
        "path_id": "49712",
        "message_size": 41.0
      },
      {
        "task_id": 16,
        "path_id": "183650",
        "message_size": 51.0
      },
      {
        "task_id": 4,
        "path_id": "183650",
        "message_size": 51.0
      },
      {
        "task_id": 20,
        "path_id": "49712",
        "message_size": 41.0
      },
      {
        "task_id": 8,
        "path_id": "183650",
        "message_size": 51.0
      },
      {
        "task_id": 26,
        "path_id": "49723",
        "message_size": 53.0
      },
      {
        "task_id": 0,
        "path_id": "49723",
        "message_size": 53.0
      },
      {
        "task_id": 32,
        "path_id": "49712",
        "message_size": 41.0
      }
    ]
  },
  {
    "node_id": 51,
    "task_id": 35,
    "start_time": 400.0000339031667,
    "end_time": 400.0000340065001,
    "dependencies": [
      {
        "task_id": 10,
        "path_id": "49712",
        "message_size": 41.0
      },
      {
        "task_id": 7,
        "path_id": "49712",
        "message_size": 41.0
      },
      {
        "task_id": 13,
        "path_id": "49723",
        "message_size": 53.0
      },
      {
        "task_id": 21,
        "path_id": "183650",
        "message_size": 51.0
      },
      {
        "task_id": 31,
        "path_id": "183650",
        "message_size": 51.0
      },
      {
        "task_id": 18,
        "path_id": "49712",
        "message_size": 41.0
      },
      {
        "task_id": 32,
        "path_id": "49712",
        "message_size": 41.0
      }
    ]
  },
  {
    "node_id": 51,
    "task_id": 41,
    "start_time": 400.0000339031667,
    "end_time": 400.0000342238334,
    "dependencies": [
      {
        "task_id": 10,
        "path_id": "49712",
        "message_size": 41.0
      },
      {
        "task_id": 39,
        "path_id": "49712",
        "message_size": 41.0
      },
      {
        "task_id": 29,
        "path_id": "183650",
        "message_size": 51.0
      },
      {
        "task_id": 4,
        "path_id": "183650",
        "message_size": 51.0
      },
      {
        "task_id": 15,
        "path_id": "49712",
        "message_size": 41.0
      },
      {
        "task_id": 31,
        "path_id": "183650",
        "message_size": 51.0
      },
      {
        "task_id": 19,
        "path_id": "49712",
        "message_size": 41.0
      },
      {
        "task_id": 0,
        "path_id": "49723",
        "message_size": 53.0
      }
    ]
  },
  {
    "node_id": 51,
    "task_id": 36,
    "start_time": 409.0000214154167,
    "end_time": 409.0000219174167,
    "dependencies": [
      {
        "task_id": 1,
        "path_id": "49723",
        "message_size": 53.0
      },
      {
        "task_id": 16,
        "path_id": "183650",
        "message_size": 51.0
      },
      {
        "task_id": 33,
        "path_id": "183650",
        "message_size": 51.0
      },
      {
        "task_id": 34,
        "path_id": "49712",
        "message_size": 41.0
      },
      {
        "task_id": 2,
        "path_id": "49723",
        "message_size": 53.0
      },
      {
        "task_id": 5,
        "path_id": "49712",
        "message_size": 41.0
      },
      {
        "task_id": 8,
        "path_id": "183650",
        "message_size": 51.0
      },
      {
        "task_id": 17,
        "path_id": "183650",
        "message_size": 51.0
      },
      {
        "task_id": 13,
        "path_id": "49723",
        "message_size": 53.0
      },
      {
        "task_id": 32,
        "path_id": "49712",
        "message_size": 41.0
      }
    ]
  },
  {
    "node_id": 51,
    "task_id": 42,
    "start_time": 409.0000219174167,
    "end_time": 409.00002230608334,
    "dependencies": [
      {
        "task_id": 9,
        "path_id": "183650",
        "message_size": 51.0
      },
      {
        "task_id": 1,
        "path_id": "49723",
        "message_size": 53.0
      },
      {
        "task_id": 7,
        "path_id": "49712",
        "message_size": 41.0
      },
      {
        "task_id": 36,
        "path_id": "183650",
        "message_size": 51.0
      },
      {
        "task_id": 6,
        "path_id": "49712",
        "message_size": 41.0
      },
      {
        "task_id": 15,
        "path_id": "49712",
        "message_size": 41.0
      },
      {
        "task_id": 18,
        "path_id": "49712",
        "message_size": 41.0
      },
      {
        "task_id": 21,
        "path_id": "183650",
        "message_size": 51.0
      },
      {
        "task_id": 31,
        "path_id": "183650",
        "message_size": 51.0
      },
      {
        "task_id": 19,
        "path_id": "49712",
        "message_size": 41.0
      }
    ]
  },
  {
    "node_id": 51,
    "task_id": 40,
    "start_time": 483.0000312584167,
    "end_time": 483.00003148775005,
    "dependencies": [
      {
        "task_id": 39,
        "path_id": "49712",
        "message_size": 41.0
      },
      {
        "task_id": 16,
        "path_id": "183650",
        "message_size": 51.0
      },
      {
        "task_id": 14,
        "path_id": "49723",
        "message_size": 53.0
      },
      {
        "task_id": 4,
        "path_id": "183650",
        "message_size": 51.0
      },
      {
        "task_id": 30,
        "path_id": "183650",
        "message_size": 51.0
      },
      {
        "task_id": 37,
        "path_id": "49712",
        "message_size": 41.0
      },
      {
        "task_id": 19,
        "path_id": "49712",
        "message_size": 41.0
      }
    ]
  },
  {
    "node_id": 51,
    "task_id": 45,
    "start_time": 501.0000342238334,
    "end_time": 501.00003464983337,
    "dependencies": [
      {
        "task_id": 9,
        "path_id": "183650",
        "message_size": 51.0
      },
      {
        "task_id": 39,
        "path_id": "49712",
        "message_size": 41.0
      },
      {
        "task_id": 16,
        "path_id": "183650",
        "message_size": 51.0
      },
      {
        "task_id": 29,
        "path_id": "183650",
        "message_size": 51.0
      },
      {
        "task_id": 41,
        "path_id": "183650",
        "message_size": 51.0
      },
      {
        "task_id": 14,
        "path_id": "49723",
        "message_size": 53.0
      },
      {
        "task_id": 27,
        "path_id": "49723",
        "message_size": 53.0
      },
      {
        "task_id": 42,
        "path_id": "183650",
        "message_size": 51.0
      },
      {
        "task_id": 23,
        "path_id": "183650",
        "message_size": 51.0
      },
      {
        "task_id": 2,
        "path_id": "49723",
        "message_size": 53.0
      },
      {
        "task_id": 5,
        "path_id": "49712",
        "message_size": 41.0
      },
      {
        "task_id": 18,
        "path_id": "49712",
        "message_size": 41.0
      },
      {
        "task_id": 26,
        "path_id": "49723",
        "message_size": 53.0
      },
      {
        "task_id": 0,
        "path_id": "49723",
        "message_size": 53.0
      }
    ]
  },
  {
    "node_id": 51,
    "task_id": 47,
    "start_time": 584.00003148775,
    "end_time": 584.00003157575,
    "dependencies": [
      {
        "task_id": 29,
        "path_id": "183650",
        "message_size": 51.0
      },
      {
        "task_id": 23,
        "path_id": "183650",
        "message_size": 51.0
      },
      {
        "task_id": 34,
        "path_id": "49712",
        "message_size": 41.0
      },
      {
        "task_id": 46,
        "path_id": "49712",
        "message_size": 41.0
      },
      {
        "task_id": 24,
        "path_id": "49712",
        "message_size": 41.0
      },
      {
        "task_id": 8,
        "path_id": "183650",
        "message_size": 51.0
      },
      {
        "task_id": 11,
        "path_id": "49712",
        "message_size": 41.0
      },
      {
        "task_id": 22,
        "path_id": "49723",
        "message_size": 53.0
      },
      {
        "task_id": 40,
        "path_id": "183650",
        "message_size": 51.0
      },
      {
        "task_id": 19,
        "path_id": "49712",
        "message_size": 41.0
      },
      {
        "task_id": 32,
        "path_id": "49712",
        "message_size": 41.0
      }
    ]
  },
  {
    "node_id": 52,
    "task_id": 5,
    "start_time": 0.0,
    "end_time": 3.3e-07,
    "dependencies": []
  },
  {
    "node_id": 52,
    "task_id": 10,
    "start_time": 93.00000056533332,
    "end_time": 93.00000079325,
    "dependencies": [
      {
        "task_id": 3,
        "path_id": "49713",
        "message_size": 43.0
      }
    ]
  },
  {
    "node_id": 52,
    "task_id": 19,
    "start_time": 102.0000269375,
    "end_time": 102.00002723624999,
    "dependencies": [
      {
        "task_id": 1,
        "path_id": "51343",
        "message_size": 52.0
      }
    ]
  },
  {
    "node_id": 52,
    "task_id": 7,
    "start_time": 102.000039875,
    "end_time": 102.00003998833333,
    "dependencies": [
      {
        "task_id": 1,
        "path_id": "51343",
        "message_size": 52.0
      },
      {
        "task_id": 3,
        "path_id": "49713",
        "message_size": 43.0
      },
      {
        "task_id": 2,
        "path_id": "51343",
        "message_size": 52.0
      }
    ]
  },
  {
    "node_id": 52,
    "task_id": 11,
    "start_time": 102.000039875,
    "end_time": 102.00004017875,
    "dependencies": [
      {
        "task_id": 4,
        "path_id": "49713",
        "message_size": 43.0
      },
      {
        "task_id": 8,
        "path_id": "49713",
        "message_size": 43.0
      },
      {
        "task_id": 2,
        "path_id": "51343",
        "message_size": 52.0
      }
    ]
  },
  {
    "node_id": 52,
    "task_id": 6,
    "start_time": 102.00008600000001,
    "end_time": 102.00008627041667,
    "dependencies": [
      {
        "task_id": 0,
        "path_id": "51343",
        "message_size": 52.0
      },
      {
        "task_id": 2,
        "path_id": "51343",
        "message_size": 52.0
      }
    ]
  },
  {
    "node_id": 52,
    "task_id": 12,
    "start_time": 196.000040059,
    "end_time": 196.00004015275002,
    "dependencies": [
      {
        "task_id": 9,
        "path_id": "49713",
        "message_size": 43.0
      }
    ]
  },
  {
    "node_id": 52,
    "task_id": 15,
    "start_time": 197.00002037583334,
    "end_time": 197.00002067625002,
    "dependencies": [
      {
        "task_id": 14,
        "path_id": "51343",
        "message_size": 52.0
      },
      {
        "task_id": 4,
        "path_id": "49713",
        "message_size": 43.0
      },
      {
        "task_id": 3,
        "path_id": "49713",
        "message_size": 43.0
      }
    ]
  },
  {
    "node_id": 52,
    "task_id": 24,
    "start_time": 197.00003031333333,
    "end_time": 197.00003050458332,
    "dependencies": [
      {
        "task_id": 19,
        "path_id": "183660",
        "message_size": 43.0
      },
      {
        "task_id": 3,
        "path_id": "49713",
        "message_size": 43.0
      },
      {
        "task_id": 13,
        "path_id": "51343",
        "message_size": 52.0
      },
      {
        "task_id": 4,
        "path_id": "49713",
        "message_size": 43.0
      },
      {
        "task_id": 0,
        "path_id": "51343",
        "message_size": 52.0
      }
    ]
  },
  {
    "node_id": 52,
    "task_id": 18,
    "start_time": 289.00004015275,
    "end_time": 289.0000403644167,
    "dependencies": [
      {
        "task_id": 16,
        "path_id": "49713",
        "message_size": 43.0
      },
      {
        "task_id": 3,
        "path_id": "49713",
        "message_size": 43.0
      },
      {
        "task_id": 7,
        "path_id": "183660",
        "message_size": 43.0
      },
      {
        "task_id": 1,
        "path_id": "51343",
        "message_size": 52.0
      },
      {
        "task_id": 12,
        "path_id": "183660",
        "message_size": 43.0
      },
      {
        "task_id": 6,
        "path_id": "183660",
        "message_size": 43.0
      }
    ]
  },
  {
    "node_id": 52,
    "task_id": 20,
    "start_time": 290.00002067625,
    "end_time": 290.0000208954167,
    "dependencies": [
      {
        "task_id": 6,
        "path_id": "183660",
        "message_size": 43.0
      },
      {
        "task_id": 15,
        "path_id": "183660",
        "message_size": 43.0
      }
    ]
  },
  {
    "node_id": 52,
    "task_id": 37,
    "start_time": 392.0000311846667,
    "end_time": 392.0000312584167,
    "dependencies": [
      {
        "task_id": 20,
        "path_id": "183660",
        "message_size": 43.0
      },
      {
        "task_id": 9,
        "path_id": "49713",
        "message_size": 43.0
      },
      {
        "task_id": 36,
        "path_id": "49713",
        "message_size": 43.0
      },
      {
        "task_id": 29,
        "path_id": "49713",
        "message_size": 43.0
      },
      {
        "task_id": 11,
        "path_id": "183660",
        "message_size": 43.0
      },
      {
        "task_id": 4,
        "path_id": "49713",
        "message_size": 43.0
      },
      {
        "task_id": 18,
        "path_id": "183660",
        "message_size": 43.0
      },
      {
        "task_id": 2,
        "path_id": "51343",
        "message_size": 52.0
      }
    ]
  },
  {
    "node_id": 52,
    "task_id": 39,
    "start_time": 392.0000311846667,
    "end_time": 392.00003137258335,
    "dependencies": [
      {
        "task_id": 16,
        "path_id": "49713",
        "message_size": 43.0
      },
      {
        "task_id": 3,
        "path_id": "49713",
        "message_size": 43.0
      },
      {
        "task_id": 35,
        "path_id": "49713",
        "message_size": 43.0
      },
      {
        "task_id": 1,
        "path_id": "51343",
        "message_size": 52.0
      },
      {
        "task_id": 29,
        "path_id": "49713",
        "message_size": 43.0
      },
      {
        "task_id": 26,
        "path_id": "51343",
        "message_size": 52.0
      },
      {
        "task_id": 12,
        "path_id": "183660",
        "message_size": 43.0
      },
      {
        "task_id": 21,
        "path_id": "49713",
        "message_size": 43.0
      },
      {
        "task_id": 6,
        "path_id": "183660",
        "message_size": 43.0
      },
      {
        "task_id": 32,
        "path_id": "183660",
        "message_size": 43.0
      }
    ]
  },
  {
    "node_id": 52,
    "task_id": 32,
    "start_time": 392.0000339031667,
    "end_time": 392.00003404025006,
    "dependencies": [
      {
        "task_id": 31,
        "path_id": "49713",
        "message_size": 43.0
      },
      {
        "task_id": 5,
        "path_id": "183660",
        "message_size": 43.0
      },
      {
        "task_id": 13,
        "path_id": "51343",
        "message_size": 52.0
      },
      {
        "task_id": 8,
        "path_id": "49713",
        "message_size": 43.0
      },
      {
        "task_id": 27,
        "path_id": "51343",
        "message_size": 52.0
      },
      {
        "task_id": 6,
        "path_id": "183660",
        "message_size": 43.0
      }
    ]
  },
  {
    "node_id": 52,
    "task_id": 38,
    "start_time": 396.0000013746667,
    "end_time": 396.00000166300003,
    "dependencies": [
      {
        "task_id": 31,
        "path_id": "49713",
        "message_size": 43.0
      },
      {
        "task_id": 35,
        "path_id": "49713",
        "message_size": 43.0
      },
      {
        "task_id": 22,
        "path_id": "51343",
        "message_size": 52.0
      },
      {
        "task_id": 29,
        "path_id": "49713",
        "message_size": 43.0
      },
      {
        "task_id": 30,
        "path_id": "49713",
        "message_size": 43.0
      },
      {
        "task_id": 8,
        "path_id": "49713",
        "message_size": 43.0
      },
      {
        "task_id": 15,
        "path_id": "183660",
        "message_size": 43.0
      }
    ]
  },
  {
    "node_id": 52,
    "task_id": 34,
    "start_time": 418.00003404025006,
    "end_time": 418.00003425441673,
    "dependencies": [
      {
        "task_id": 22,
        "path_id": "51343",
        "message_size": 52.0
      },
      {
        "task_id": 29,
        "path_id": "49713",
        "message_size": 43.0
      },
      {
        "task_id": 25,
        "path_id": "49713",
        "message_size": 43.0
      },
      {
        "task_id": 32,
        "path_id": "183660",
        "message_size": 43.0
      }
    ]
  },
  {
    "node_id": 52,
    "task_id": 44,
    "start_time": 576.00003148775,
    "end_time": 576.0000315448333,
    "dependencies": [
      {
        "task_id": 19,
        "path_id": "183660",
        "message_size": 43.0
      },
      {
        "task_id": 35,
        "path_id": "49713",
        "message_size": 43.0
      },
      {
        "task_id": 1,
        "path_id": "51343",
        "message_size": 52.0
      },
      {
        "task_id": 29,
        "path_id": "49713",
        "message_size": 43.0
      },
      {
        "task_id": 26,
        "path_id": "51343",
        "message_size": 52.0
      },
      {
        "task_id": 4,
        "path_id": "49713",
        "message_size": 43.0
      },
      {
        "task_id": 27,
        "path_id": "51343",
        "message_size": 52.0
      },
      {
        "task_id": 34,
        "path_id": "183660",
        "message_size": 43.0
      },
      {
        "task_id": 21,
        "path_id": "49713",
        "message_size": 43.0
      },
      {
        "task_id": 40,
        "path_id": "49713",
        "message_size": 43.0
      }
    ]
  },
  {
    "node_id": 52,
    "task_id": 46,
    "start_time": 576.00003148775,
    "end_time": 576.0000317119167,
    "dependencies": [
      {
        "task_id": 9,
        "path_id": "49713",
        "message_size": 43.0
      },
      {
        "task_id": 22,
        "path_id": "51343",
        "message_size": 52.0
      },
      {
        "task_id": 29,
        "path_id": "49713",
        "message_size": 43.0
      },
      {
        "task_id": 0,
        "path_id": "51343",
        "message_size": 52.0
      },
      {
        "task_id": 27,
        "path_id": "51343",
        "message_size": 52.0
      },
      {
        "task_id": 40,
        "path_id": "49713",
        "message_size": 43.0
      }
    ]
  },
  {
    "node_id": 53,
    "task_id": 0,
    "start_time": 0.0,
    "end_time": 2.6312500000000003e-05,
    "dependencies": []
  },
  {
    "node_id": 53,
    "task_id": 1,
    "start_time": 0.0,
    "end_time": 2.69375e-05,
    "dependencies": []
  },
  {
    "node_id": 53,
    "task_id": 2,
    "start_time": 0.0,
    "end_time": 3.9875e-05,
    "dependencies": []
  },
  {
    "node_id": 53,
    "task_id": 13,
    "start_time": 95.00000056533332,
    "end_time": 95.00003031533332,
    "dependencies": [
      {
        "task_id": 8,
        "path_id": "49722",
        "message_size": 45.0
      },
      {
        "task_id": 4,
        "path_id": "49722",
        "message_size": 45.0
      },
      {
        "task_id": 3,
        "path_id": "49722",
        "message_size": 45.0
      },
      {
        "task_id": 0,
        "path_id": "183670",
        "message_size": 32.0
      }
    ]
  },
  {
    "node_id": 53,
    "task_id": 14,
    "start_time": 95.00000056533332,
    "end_time": 95.00002037783332,
    "dependencies": [
      {
        "task_id": 8,
        "path_id": "49722",
        "message_size": 45.0
      },
      {
        "task_id": 3,
        "path_id": "49722",
        "message_size": 45.0
      }
    ]
  },
  {
    "node_id": 53,
    "task_id": 22,
    "start_time": 196.00004014541668,
    "end_time": 196.00007270791667,
    "dependencies": [
      {
        "task_id": 21,
        "path_id": "49722",
        "message_size": 45.0
      },
      {
        "task_id": 13,
        "path_id": "183670",
        "message_size": 32.0
      },
      {
        "task_id": 19,
        "path_id": "00",
        "message_size": 44.0
      },
      {
        "task_id": 6,
        "path_id": "00",
        "message_size": 44.0
      }
    ]
  },
  {
    "node_id": 53,
    "task_id": 27,
    "start_time": 259.0000462508333,
    "end_time": 259.00008312583327,
    "dependencies": [
      {
        "task_id": 21,
        "path_id": "49722",
        "message_size": 45.0
      },
      {
        "task_id": 7,
        "path_id": "00",
        "message_size": 44.0
      },
      {
        "task_id": 26,
        "path_id": "183670",
        "message_size": 32.0
      },
      {
        "task_id": 2,
        "path_id": "183670",
        "message_size": 32.0
      }
    ]
  },
  {
    "node_id": 53,
    "task_id": 26,
    "start_time": 291.00002067625,
    "end_time": 291.00003661375,
    "dependencies": [
      {
        "task_id": 9,
        "path_id": "49722",
        "message_size": 45.0
      },
      {
        "task_id": 3,
        "path_id": "49722",
        "message_size": 45.0
      },
      {
        "task_id": 13,
        "path_id": "183670",
        "message_size": 32.0
      },
      {
        "task_id": 17,
        "path_id": "49722",
        "message_size": 45.0
      },
      {
        "task_id": 6,
        "path_id": "00",
        "message_size": 44.0
      },
      {
        "task_id": 15,
        "path_id": "00",
        "message_size": 44.0
      },
      {
        "task_id": 2,
        "path_id": "183670",
        "message_size": 32.0
      }
    ]
  },
  {
    "node_id": 53,
    "task_id": 43,
    "start_time": 486.0000312584167,
    "end_time": 486.0000569459167,
    "dependencies": [
      {
        "task_id": 32,
        "path_id": "00",
        "message_size": 44.0
      },
      {
        "task_id": 37,
        "path_id": "00",
        "message_size": 44.0
      },
      {
        "task_id": 42,
        "path_id": "49722",
        "message_size": 45.0
      },
      {
        "task_id": 8,
        "path_id": "49722",
        "message_size": 45.0
      },
      {
        "task_id": 38,
        "path_id": "00",
        "message_size": 44.0
      }
    ]
  },
  {
    "node_id": 53,
    "task_id": 49,
    "start_time": 578.00003148775,
    "end_time": 578.00006642525,
    "dependencies": [
      {
        "task_id": 9,
        "path_id": "49722",
        "message_size": 45.0
      },
      {
        "task_id": 44,
        "path_id": "00",
        "message_size": 44.0
      },
      {
        "task_id": 25,
        "path_id": "49722",
        "message_size": 45.0
      },
      {
        "task_id": 35,
        "path_id": "49722",
        "message_size": 45.0
      },
      {
        "task_id": 11,
        "path_id": "00",
        "message_size": 44.0
      },
      {
        "task_id": 15,
        "path_id": "00",
        "message_size": 44.0
      },
      {
        "task_id": 8,
        "path_id": "49722",
        "message_size": 45.0
      },
      {
        "task_id": 40,
        "path_id": "49722",
        "message_size": 45.0
      }
    ]
  }
]